{"subject":"RE: 188735-HF 8 Vs. CGML","content":"Hi Team,\r\n\r\n \r\n\r\nPlease return EUR 720,000 as per margin statement.\r\n\r\n \r\n\r\n \r\n\r\n \r\n\r\n \r\n\r\nxxxxx xxxxxxxx\r\n\r\nxxxxxxx xxxxxxx\r\n\r\n111 xxxxxx xxxxxx xxxxx xxxx xxx \r\n\r\nTel: +11 11 1111111\r\n\r\nEmail: xxxxx.xxxxxxx@xxxxxxx.xxx\r\n\r\nwww.xxxxxx.com\r\n\r\n \r\n\r\n \r\n\r\n \r\n\r\nFrom: XXXXXXX@XXXX.xxx [mailto: XXXXXXX@XXXX.xxx]\r\nSent: 05 September 2018 10:30\r\nTo: xxxxxxxxx@xxxx.xxx; Xxxxx & Xxxxxxxxxxxx XX\r\nCc: XXXXXXX.xxxx@XXXX.xxx\r\nSubject: 188735-HF 8 Vs. CGML\r\n\r\n \r\n\r\n \r\n\r\n\r\n\r\nPlease find attached portfolio statement as of 04-Sep-18\r\n\r\nRegards,\r\nCGML\r\n\r\nGroup Email: xxxxxxxxxx@xxxx.xxx\r\nGroup Tel#: +11-11-111-1111\r\n\r\nThe information contained in this electronic message and any attachments (the \\\"Message\\\") is intended for one or more specific individuals or entities, and may be confidential, proprietary, or otherwise protected by law. If you are not the intended recipient, please notify the sender immediately, delete this Message and do not disclose, distribute, or copy it to any third party or otherwise use this Message. Electronic messages are not secure or error free and can contain viruses or may be delayed, and the sender is not liable for any of these occurrences. The sender reserves the right to monitor, record transfer cross border and retain electronic messages.\r\n\r\n \r\n\r\n \r\n\r\n","from":"gm22891@imceu.eu.ssmb.com Mcclafferty, Gary [ICG-IT]","to":"","attachments":[]}